setuptools_proto.py
setuptools_proto-1.0.0.dist-info/LICENSE
setuptools_proto-1.0.0.dist-info/METADATA
setuptools_proto-1.0.0.dist-info/WHEEL
setuptools_proto-1.0.0.dist-info/entry_points.txt
setuptools_proto-1.0.0.dist-info/top_level.txt
setuptools_proto-1.0.0.dist-info/RECORD
