Metadata-Version: 2.1
Name: setuptools-proto
Version: 1.0.0
Summary: setuptools plugin to generate python file from protobuf
Home-page: https://github.com/jameslan/setuptools-proto
Author: James Lan
Author-email: jameslan@gmail.com
License: Apache License 2.0
Platform: UNKNOWN
Classifier: Programming Language :: Python :: 3
Classifier: Programming Language :: Python :: 3.6
Classifier: Programming Language :: Python :: 3.7
Classifier: Programming Language :: Python :: 3.8
Classifier: Framework :: Setuptools Plugin
Classifier: Intended Audience :: Developers
Classifier: License :: OSI Approved :: Apache Software License
Requires-Python: >=3.6
Requires-Dist: setuptools-cmd-deps
